README.rst
setup.py
FSE22_CAT/__init__.py
FSE22_CAT.egg-info/PKG-INFO
FSE22_CAT.egg-info/SOURCES.txt
FSE22_CAT.egg-info/dependency_links.txt
FSE22_CAT.egg-info/top_level.txt